flaremodel.libs/libsatlas-7e2f78d2.so.3.10
flaremodel.libs/libquadmath-96973f99.so.0.0.0
flaremodel.libs/libgomp-a34b3233.so.1.0.0
flaremodel.libs/libgsl-cb3064f9.so.0.16.0
flaremodel.libs/libgslcblas-9055a056.so.0.0.0
flaremodel.libs/libgfortran-91cc3cb1.so.3.0.0
flaremodel-1.0.3.dist-info/LICENSE
flaremodel-1.0.3.dist-info/RECORD
flaremodel-1.0.3.dist-info/top_level.txt
flaremodel-1.0.3.dist-info/WHEEL
flaremodel-1.0.3.dist-info/METADATA
flaremodel/geometry.py
flaremodel/fitting.py
flaremodel/__init__.py
flaremodel/temporal.py
flaremodel/plotctrl.py
flaremodel/utils/__init__.py
flaremodel/utils/gfuncs.py
flaremodel/utils/cfuncs.cpython-37m-x86_64-linux-gnu.so
flaremodel/utils/utils.py
flaremodel/utils/constants.py
flaremodel/sources/sgrA.py
flaremodel/sources/__init__.py
flaremodel/tests/__init__.py
flaremodel/tests/test_synchrotron.py
flaremodel/tests/test_edist.py
