Metadata-Version: 2.1
Name: flaremodel
Version: 1.0.3
Summary: A simple one zone code that can do many different flavours of flares
Home-page: https://github.com/ydallilar/flaremodel/
Author: Yigit Dallilar, Sebastiano von Fellenberg
Author-email: ydallilar@mpe.mpg.de, sefe@mpe.mpg.de
License: UNKNOWN
Platform: UNKNOWN
